button_execute/__init__.py
button_execute/_version.py
button_execute/button_execute.py
button_execute/static/extension.js
button_execute/static/index.js
button_execute/static/index.js.map
button_execute-0.3.0.data/data/etc/jupyter/nbconfig/notebook.d/jupyter-button_execute.json
button_execute-0.3.0.data/data/share/jupyter/nbextensions/jupyter-button_execute/extension.js
button_execute-0.3.0.data/data/share/jupyter/nbextensions/jupyter-button_execute/index.js
button_execute-0.3.0.data/data/share/jupyter/nbextensions/jupyter-button_execute/index.js.map
button_execute-0.3.0.dist-info/DESCRIPTION.rst
button_execute-0.3.0.dist-info/METADATA
button_execute-0.3.0.dist-info/RECORD
button_execute-0.3.0.dist-info/WHEEL
button_execute-0.3.0.dist-info/metadata.json
button_execute-0.3.0.dist-info/top_level.txt
