Metadata-Version: 2.0
Name: button-execute
Version: 0.3.0
Summary: Jupyter notebook button to execute subsequent cells
Home-page: https://github.com/ProtProtocols/jupyter-button_execute
Author: Johannes Griss
Author-email: johannes.griss@meduniwien.ac.at
License: UNKNOWN
Keywords: ipython,jupyter,widgets
Platform: UNKNOWN
Classifier: Development Status :: 4 - Beta
Classifier: Framework :: IPython
Classifier: Intended Audience :: Developers
Classifier: Intended Audience :: Science/Research
Classifier: Topic :: Multimedia :: Graphics
Classifier: Programming Language :: Python :: 3.3
Classifier: Programming Language :: Python :: 3.4
Classifier: Programming Language :: Python :: 3.5
Requires-Dist: ipywidgets (>=7.0.0)
